{"server_type": "forge", "server_version": "1.19.2", "version_jdk": "17", "gbs_de_ram_a_usar": 12, "servicio_a_usar": "playit", "actualizaciones_discord": true, "webhook_de_discord": "https://discord.com/api/webhooks/1473836047203831809/CEi7Vq3bYiQhr8R59nAVig6KemNtElYaYamQmc1quXvc8tfAz8OzApbzc8dkrPWHj_DI", "iniciando_servidor": true, "decir_ip": true, "usar_dropbox": false, "token_dropbox": "", "debug_mode": true, "flags": "-Xms2G -Xmx12G", "zerotier_network": "", "backup_mode": "", "backup_auto": false, "online-mode": false, "donotaskupdate": true, "billing_activado": true, "auto_apagar": true}